<?xml version="1.0" encoding="UTF-8"?>
<ti:app xmlns:ti="http://ti.appcelerator.org">
    <id>smartj.marinos</id>
    <name>SmartJ for Marinos</name>
    <version>1.1.0</version>
    <publisher>Motoi Kataoka</publisher>
    <url>http://motoy3d.blogspot.com</url>
    <description>横浜F・マリノスアプリ！</description>
    <copyright>2018 by Motoi Kataoka</copyright>
    <icon>appicon.png</icon>
    <fullscreen>false</fullscreen>
    <navbar-hidden>false</navbar-hidden>
    <analytics>false</analytics>
    <guid>6445d8a9-1b91-40fd-9aaa-8b75a0af068a</guid>
    <property name="ti.ui.defaultunit" type="string">dp</property>
    <ios>
        <min-ios-ver>8.0</min-ios-ver>
        <plist>
            <dict>
                <key>UISupportedInterfaceOrientations~iphone</key>
                <array>
                    <string>UIInterfaceOrientationPortrait</string>
                </array>
                <key>UIRequiresPersistentWiFi</key>
                <false/>
                <key>UIPrerenderedIcon</key>
                <false/>
                <key>UIStatusBarHidden</key>
                <false/>
                <key>UIStatusBarStyle</key>
                <string>UIStatusBarStyleLightContent</string>
            </dict>
        </plist>
        <statusbar-hidden>false</statusbar-hidden>
        <fullscreen>false</fullscreen>
        <orientations device="iphone">
            <orientation>Ti.UI.PORTRAIT</orientation>
        </orientations>
        <orientations device="ipad">
            <orientation>Ti.UI.PORTRAIT</orientation>
            <orientation>Ti.UI.UPSIDE_PORTRAIT</orientation>
            <orientation>Ti.UI.LANDSCAPE_LEFT</orientation>
            <orientation>Ti.UI.LANDSCAPE_RIGHT</orientation>
        </orientations>
    </ios>
    <android xmlns:android="http://schemas.android.com/apk/res/android"/>
    <!-- Android設定はplatform/android/AndroidManifest.xmlで行う。
    WRITE_EXTERNAL_STORAGEパーミッションを無効化するのがtiapp.xmlではできないため -->
    <android xmlns:android="http://schemas.android.com/apk/res/android"/>
    <!-- Android設定はplatform/android/AndroidManifest.xmlで行う。
    WRITE_EXTERNAL_STORAGEパーミッションを無効化するのがtiapp.xmlではできないため -->
    <modules>
        <module platform="iphone">de.marcelpociot.social</module>
    </modules>
    <deployment-targets>
        <target device="android">true</target>
        <target device="ipad">false</target>
        <target device="iphone">true</target>
    </deployment-targets>
    <sdk-version>7.5.0.GA</sdk-version>
    <property name="appc-app-id" type="string">57d276a87b19ac043d16e17d</property>
    <property name="appc-org-id" type="string">100001606</property>
    <property name="appc-creator-user-id" type="string">0c8920b0-9a23-4f31-b3ce-c00f6d1cdb46</property>
</ti:app>
